color_fish.py
color_fish-0.1.3.dist-info/WHEEL
color_fish-0.1.3.dist-info/METADATA
color_fish-0.1.3.dist-info/RECORD
