Metadata-Version: 2.1
Name: color-fish
Version: 0.1.3
Summary: fish()
Author: pavelsv
Author-email: p6282813@yandex.ru
Requires-Python: >=3.7,<4.0
Classifier: Programming Language :: Python :: 3
Classifier: Programming Language :: Python :: 3.7
Classifier: Programming Language :: Python :: 3.8
Classifier: Programming Language :: Python :: 3.9
Classifier: Programming Language :: Python :: 3.10
